whisp/__init__.py
whisp/client/WhispClient.py
whisp/client/__init__.py
whisp/external/Event.py
whisp/external/__init__.py
whisp/messages/NetworkMessages.py
whisp/messages/WhispMessage.py
whisp/messages/__init__.py
whisp/server/WhispConnection.py
whisp/server/WhispServer.py
whisp/server/__init__.py
whisp/server/_templates/__init__.py
whisp/server/_templates/index.html.jinja
whisp/server/_templates/static/__init__.py
whisp/server/_templates/static/main.js
whisp/server/_templates/static/style.css
whisp/server/_templates/static/whisp.js
whisp/server/code/BaseCodeGenerator.py
whisp/server/code/CSharpCodeGenerator.py
whisp/server/code/IntermediateLanguage.py
whisp/server/code/JavaScriptCodeGenerator.py
whisp/server/code/PythonCodeGenerator.py
whisp/server/code/__init__.py
whisp/server/code/_templates/__init__.py
whisp/server/code/_templates/csharp.cs.jinja
whisp/server/code/_templates/javascript.js.jinja
whisp/server/code/_templates/python.py.jinja
whisp_net-0.1.4.dist-info/LICENSE
whisp_net-0.1.4.dist-info/METADATA
whisp_net-0.1.4.dist-info/WHEEL
whisp_net-0.1.4.dist-info/top_level.txt
whisp_net-0.1.4.dist-info/RECORD
